pyalchemyadmin/__init__.py
pyalchemyadmin/db_manager.py
pyalchemyadmin/dialect_db_manager.py
pyalchemyadmin-0.1.0b1.dist-info/LICENSE.txt
pyalchemyadmin-0.1.0b1.dist-info/METADATA
pyalchemyadmin-0.1.0b1.dist-info/WHEEL
pyalchemyadmin-0.1.0b1.dist-info/top_level.txt
pyalchemyadmin-0.1.0b1.dist-info/RECORD
