Metadata-Version: 2.1
Name: pyalchemyadmin
Version: 0.1.0b1
Summary: Database management tool for SQLAlchemy
Author-email: Elliot Su <sodinfeliz@google.com>
License: Copyright (c) 2024, Elliot Su.
Project-URL: soucre, https://github.com/sodinfeliz/PyAlchemyAdmin
Classifier: License :: OSI Approved :: BSD License
Classifier: Programming Language :: Python :: 3
Classifier: Programming Language :: Python :: 3 :: Only
Classifier: Operating System :: OS Independent
Requires-Python: >=3.8
License-File: LICENSE.txt
Requires-Dist: sqlalchemy
